Lab93CryptographyAPI/__init__.py
Lab93CryptographyAPI-0.0.1.dist-info/METADATA
Lab93CryptographyAPI-0.0.1.dist-info/WHEEL
Lab93CryptographyAPI-0.0.1.dist-info/top_level.txt
Lab93CryptographyAPI-0.0.1.dist-info/RECORD
