Metadata-Version: 2.1
Name: Lab93CryptographyAPI
Version: 0.0.1
Summary: A wrapper for python encryption to aid in the use of one-way and two-way encryption.
Author-email: Hunter Dale <hunter.g.dale@gmail.com>
Project-URL: Homepage, https://github.com/guyyatsu/Lab93Cryptogram
Project-URL: Bug Tracker, https://github.com/guyyatsu/Lab93Cryptogram/issues
Classifier: Programming Language :: Python :: 3
Classifier: License :: OSI Approved :: MIT License
Classifier: Operating System :: OS Independent
Requires-Python: >=3.10
Requires-Dist: cryptography
